[[{"citationID":"5XOFTIJT9X","citationItems":[{"id":"a0bt8du2g4"}],"properties":{"noteIndex":26}},[["SXDNEKR5AD",1],["JZNLFQX4O5",2],["RTME11VFU2",3],["9JDU56GUQE",4],["JR7944MVMF",5],["B7KJGSND3J",6],["QJKXYRLACJ",7],["K3PGTSPU9E",8],["870U89B4O6",9],["V1HIAG33VN",10],["GWZBYXJOVX",11],["1LAD2NKKUR",12],["ACUM2NWUN9",13],["KPR2HM6PKU",14],["UD7UY63FOU",15],["LKS4B7MS3Y",16],["S7YHQE56TF",17],["WC0FYV6D60",18],["OWVL2EE0AM",19],["TA1394EMR0",20],["X23KK2PY99",21],["NUZQT03DUU",22],["4R3JIJ120E",23],["G5FAQWKKRW",24],["XGR2ARHDL8",25]],[]],[{"citationID":"53D2HL9OFD","citationItems":[{"id":"6zr2hnhlkm"}],"properties":{"noteIndex":27}},[["SXDNEKR5AD",1],["JZNLFQX4O5",2],["RTME11VFU2",3],["9JDU56GUQE",4],["JR7944MVMF",5],["B7KJGSND3J",6],["QJKXYRLACJ",7],["K3PGTSPU9E",8],["870U89B4O6",9],["V1HIAG33VN",10],["GWZBYXJOVX",11],["1LAD2NKKUR",12],["ACUM2NWUN9",13],["KPR2HM6PKU",14],["UD7UY63FOU",15],["LKS4B7MS3Y",16],["S7YHQE56TF",17],["WC0FYV6D60",18],["OWVL2EE0AM",19],["TA1394EMR0",20],["X23KK2PY99",21],["NUZQT03DUU",22],["4R3JIJ120E",23],["G5FAQWKKRW",24],["XGR2ARHDL8",25],["5XOFTIJT9X",26]],[]],[{"citationID":"WVMT9BHAAL","citationItems":[{"id":"w1vda9wk1w"}],"properties":{"noteIndex":28}},[["SXDNEKR5AD",1],["JZNLFQX4O5",2],["RTME11VFU2",3],["9JDU56GUQE",4],["JR7944MVMF",5],["B7KJGSND3J",6],["QJKXYRLACJ",7],["K3PGTSPU9E",8],["870U89B4O6",9],["V1HIAG33VN",10],["GWZBYXJOVX",11],["1LAD2NKKUR",12],["ACUM2NWUN9",13],["KPR2HM6PKU",14],["UD7UY63FOU",15],["LKS4B7MS3Y",16],["S7YHQE56TF",17],["WC0FYV6D60",18],["OWVL2EE0AM",19],["TA1394EMR0",20],["X23KK2PY99",21],["NUZQT03DUU",22],["4R3JIJ120E",23],["G5FAQWKKRW",24],["XGR2ARHDL8",25],["5XOFTIJT9X",26],["53D2HL9OFD",27]],[]],[{"citationID":"V7ILMROZVK","citationItems":[{"id":"6eanr3cveb"}],"properties":{"noteIndex":29}},[["SXDNEKR5AD",1],["JZNLFQX4O5",2],["RTME11VFU2",3],["9JDU56GUQE",4],["JR7944MVMF",5],["B7KJGSND3J",6],["QJKXYRLACJ",7],["K3PGTSPU9E",8],["870U89B4O6",9],["V1HIAG33VN",10],["GWZBYXJOVX",11],["1LAD2NKKUR",12],["ACUM2NWUN9",13],["KPR2HM6PKU",14],["UD7UY63FOU",15],["LKS4B7MS3Y",16],["S7YHQE56TF",17],["WC0FYV6D60",18],["OWVL2EE0AM",19],["TA1394EMR0",20],["X23KK2PY99",21],["NUZQT03DUU",22],["4R3JIJ120E",23],["G5FAQWKKRW",24],["XGR2ARHDL8",25],["5XOFTIJT9X",26],["53D2HL9OFD",27],["WVMT9BHAAL",28]],[]],[{"citationID":"4586DRJ2J6","citationItems":[{"id":"nba7z5k0bh"}],"properties":{"noteIndex":30}},[["SXDNEKR5AD",1],["JZNLFQX4O5",2],["RTME11VFU2",3],["9JDU56GUQE",4],["JR7944MVMF",5],["B7KJGSND3J",6],["QJKXYRLACJ",7],["K3PGTSPU9E",8],["870U89B4O6",9],["V1HIAG33VN",10],["GWZBYXJOVX",11],["1LAD2NKKUR",12],["ACUM2NWUN9",13],["KPR2HM6PKU",14],["UD7UY63FOU",15],["LKS4B7MS3Y",16],["S7YHQE56TF",17],["WC0FYV6D60",18],["OWVL2EE0AM",19],["TA1394EMR0",20],["X23KK2PY99",21],["NUZQT03DUU",22],["4R3JIJ120E",23],["G5FAQWKKRW",24],["XGR2ARHDL8",25],["5XOFTIJT9X",26],["53D2HL9OFD",27],["WVMT9BHAAL",28],["V7ILMROZVK",29]],[]],[{"citationID":"X143BO1JQO","citationItems":[{"id":"wpnl1hzujk"}],"properties":{"noteIndex":31}},[["SXDNEKR5AD",1],["JZNLFQX4O5",2],["RTME11VFU2",3],["9JDU56GUQE",4],["JR7944MVMF",5],["B7KJGSND3J",6],["QJKXYRLACJ",7],["K3PGTSPU9E",8],["870U89B4O6",9],["V1HIAG33VN",10],["GWZBYXJOVX",11],["1LAD2NKKUR",12],["ACUM2NWUN9",13],["KPR2HM6PKU",14],["UD7UY63FOU",15],["LKS4B7MS3Y",16],["S7YHQE56TF",17],["WC0FYV6D60",18],["OWVL2EE0AM",19],["TA1394EMR0",20],["X23KK2PY99",21],["NUZQT03DUU",22],["4R3JIJ120E",23],["G5FAQWKKRW",24],["XGR2ARHDL8",25],["5XOFTIJT9X",26],["53D2HL9OFD",27],["WVMT9BHAAL",28],["V7ILMROZVK",29],["4586DRJ2J6",30]],[]],[{"citationID":"HX39QCLQU6","citationItems":[{"id":"xi2n6sk4s0"}],"properties":{"noteIndex":32}},[["SXDNEKR5AD",1],["JZNLFQX4O5",2],["RTME11VFU2",3],["9JDU56GUQE",4],["JR7944MVMF",5],["B7KJGSND3J",6],["QJKXYRLACJ",7],["K3PGTSPU9E",8],["870U89B4O6",9],["V1HIAG33VN",10],["GWZBYXJOVX",11],["1LAD2NKKUR",12],["ACUM2NWUN9",13],["KPR2HM6PKU",14],["UD7UY63FOU",15],["LKS4B7MS3Y",16],["S7YHQE56TF",17],["WC0FYV6D60",18],["OWVL2EE0AM",19],["TA1394EMR0",20],["X23KK2PY99",21],["NUZQT03DUU",22],["4R3JIJ120E",23],["G5FAQWKKRW",24],["XGR2ARHDL8",25],["5XOFTIJT9X",26],["53D2HL9OFD",27],["WVMT9BHAAL",28],["V7ILMROZVK",29],["4586DRJ2J6",30],["X143BO1JQO",31]],[]],[{"citationID":"S5FCJGXOG7","citationItems":[{"id":"km56k03fn8"}],"properties":{"noteIndex":33}},[["SXDNEKR5AD",1],["JZNLFQX4O5",2],["RTME11VFU2",3],["9JDU56GUQE",4],["JR7944MVMF",5],["B7KJGSND3J",6],["QJKXYRLACJ",7],["K3PGTSPU9E",8],["870U89B4O6",9],["V1HIAG33VN",10],["GWZBYXJOVX",11],["1LAD2NKKUR",12],["ACUM2NWUN9",13],["KPR2HM6PKU",14],["UD7UY63FOU",15],["LKS4B7MS3Y",16],["S7YHQE56TF",17],["WC0FYV6D60",18],["OWVL2EE0AM",19],["TA1394EMR0",20],["X23KK2PY99",21],["NUZQT03DUU",22],["4R3JIJ120E",23],["G5FAQWKKRW",24],["XGR2ARHDL8",25],["5XOFTIJT9X",26],["53D2HL9OFD",27],["WVMT9BHAAL",28],["V7ILMROZVK",29],["4586DRJ2J6",30],["X143BO1JQO",31],["HX39QCLQU6",32]],[]],[{"citationID":"KZWGCJDHLK","citationItems":[{"id":"eaukzxfpk8"}],"properties":{"noteIndex":34}},[["SXDNEKR5AD",1],["JZNLFQX4O5",2],["RTME11VFU2",3],["9JDU56GUQE",4],["JR7944MVMF",5],["B7KJGSND3J",6],["QJKXYRLACJ",7],["K3PGTSPU9E",8],["870U89B4O6",9],["V1HIAG33VN",10],["GWZBYXJOVX",11],["1LAD2NKKUR",12],["ACUM2NWUN9",13],["KPR2HM6PKU",14],["UD7UY63FOU",15],["LKS4B7MS3Y",16],["S7YHQE56TF",17],["WC0FYV6D60",18],["OWVL2EE0AM",19],["TA1394EMR0",20],["X23KK2PY99",21],["NUZQT03DUU",22],["4R3JIJ120E",23],["G5FAQWKKRW",24],["XGR2ARHDL8",25],["5XOFTIJT9X",26],["53D2HL9OFD",27],["WVMT9BHAAL",28],["V7ILMROZVK",29],["4586DRJ2J6",30],["X143BO1JQO",31],["HX39QCLQU6",32],["S5FCJGXOG7",33]],[]],[{"citationID":"M4BQCYHL0P","citationItems":[{"id":"xjzd7wyj1v"}],"properties":{"noteIndex":35}},[["SXDNEKR5AD",1],["JZNLFQX4O5",2],["RTME11VFU2",3],["9JDU56GUQE",4],["JR7944MVMF",5],["B7KJGSND3J",6],["QJKXYRLACJ",7],["K3PGTSPU9E",8],["870U89B4O6",9],["V1HIAG33VN",10],["GWZBYXJOVX",11],["1LAD2NKKUR",12],["ACUM2NWUN9",13],["KPR2HM6PKU",14],["UD7UY63FOU",15],["LKS4B7MS3Y",16],["S7YHQE56TF",17],["WC0FYV6D60",18],["OWVL2EE0AM",19],["TA1394EMR0",20],["X23KK2PY99",21],["NUZQT03DUU",22],["4R3JIJ120E",23],["G5FAQWKKRW",24],["XGR2ARHDL8",25],["5XOFTIJT9X",26],["53D2HL9OFD",27],["WVMT9BHAAL",28],["V7ILMROZVK",29],["4586DRJ2J6",30],["X143BO1JQO",31],["HX39QCLQU6",32],["S5FCJGXOG7",33],["KZWGCJDHLK",34]],[]],[{"citationID":"FCK6LAJH3O","citationItems":[{"id":"876mvdbth0"}],"properties":{"noteIndex":36}},[["SXDNEKR5AD",1],["JZNLFQX4O5",2],["RTME11VFU2",3],["9JDU56GUQE",4],["JR7944MVMF",5],["B7KJGSND3J",6],["QJKXYRLACJ",7],["K3PGTSPU9E",8],["870U89B4O6",9],["V1HIAG33VN",10],["GWZBYXJOVX",11],["1LAD2NKKUR",12],["ACUM2NWUN9",13],["KPR2HM6PKU",14],["UD7UY63FOU",15],["LKS4B7MS3Y",16],["S7YHQE56TF",17],["WC0FYV6D60",18],["OWVL2EE0AM",19],["TA1394EMR0",20],["X23KK2PY99",21],["NUZQT03DUU",22],["4R3JIJ120E",23],["G5FAQWKKRW",24],["XGR2ARHDL8",25],["5XOFTIJT9X",26],["53D2HL9OFD",27],["WVMT9BHAAL",28],["V7ILMROZVK",29],["4586DRJ2J6",30],["X143BO1JQO",31],["HX39QCLQU6",32],["S5FCJGXOG7",33],["KZWGCJDHLK",34],["M4BQCYHL0P",35]],[]],[{"citationID":"2BOF6Z1SJC","citationItems":[{"id":"psbv5dmrc6"}],"properties":{"noteIndex":37}},[["SXDNEKR5AD",1],["JZNLFQX4O5",2],["RTME11VFU2",3],["9JDU56GUQE",4],["JR7944MVMF",5],["B7KJGSND3J",6],["QJKXYRLACJ",7],["K3PGTSPU9E",8],["870U89B4O6",9],["V1HIAG33VN",10],["GWZBYXJOVX",11],["1LAD2NKKUR",12],["ACUM2NWUN9",13],["KPR2HM6PKU",14],["UD7UY63FOU",15],["LKS4B7MS3Y",16],["S7YHQE56TF",17],["WC0FYV6D60",18],["OWVL2EE0AM",19],["TA1394EMR0",20],["X23KK2PY99",21],["NUZQT03DUU",22],["4R3JIJ120E",23],["G5FAQWKKRW",24],["XGR2ARHDL8",25],["5XOFTIJT9X",26],["53D2HL9OFD",27],["WVMT9BHAAL",28],["V7ILMROZVK",29],["4586DRJ2J6",30],["X143BO1JQO",31],["HX39QCLQU6",32],["S5FCJGXOG7",33],["KZWGCJDHLK",34],["M4BQCYHL0P",35],["FCK6LAJH3O",36]],[]],[{"citationID":"QGNCV3B8PT","citationItems":[{"id":"ej4f7422m5"}],"properties":{"noteIndex":38}},[["SXDNEKR5AD",1],["JZNLFQX4O5",2],["RTME11VFU2",3],["9JDU56GUQE",4],["JR7944MVMF",5],["B7KJGSND3J",6],["QJKXYRLACJ",7],["K3PGTSPU9E",8],["870U89B4O6",9],["V1HIAG33VN",10],["GWZBYXJOVX",11],["1LAD2NKKUR",12],["ACUM2NWUN9",13],["KPR2HM6PKU",14],["UD7UY63FOU",15],["LKS4B7MS3Y",16],["S7YHQE56TF",17],["WC0FYV6D60",18],["OWVL2EE0AM",19],["TA1394EMR0",20],["X23KK2PY99",21],["NUZQT03DUU",22],["4R3JIJ120E",23],["G5FAQWKKRW",24],["XGR2ARHDL8",25],["5XOFTIJT9X",26],["53D2HL9OFD",27],["WVMT9BHAAL",28],["V7ILMROZVK",29],["4586DRJ2J6",30],["X143BO1JQO",31],["HX39QCLQU6",32],["S5FCJGXOG7",33],["KZWGCJDHLK",34],["M4BQCYHL0P",35],["FCK6LAJH3O",36],["2BOF6Z1SJC",37]],[]],[{"citationID":"VH88NA6MPB","citationItems":[{"id":"mcmtlganfy"}],"properties":{"noteIndex":39}},[["SXDNEKR5AD",1],["JZNLFQX4O5",2],["RTME11VFU2",3],["9JDU56GUQE",4],["JR7944MVMF",5],["B7KJGSND3J",6],["QJKXYRLACJ",7],["K3PGTSPU9E",8],["870U89B4O6",9],["V1HIAG33VN",10],["GWZBYXJOVX",11],["1LAD2NKKUR",12],["ACUM2NWUN9",13],["KPR2HM6PKU",14],["UD7UY63FOU",15],["LKS4B7MS3Y",16],["S7YHQE56TF",17],["WC0FYV6D60",18],["OWVL2EE0AM",19],["TA1394EMR0",20],["X23KK2PY99",21],["NUZQT03DUU",22],["4R3JIJ120E",23],["G5FAQWKKRW",24],["XGR2ARHDL8",25],["5XOFTIJT9X",26],["53D2HL9OFD",27],["WVMT9BHAAL",28],["V7ILMROZVK",29],["4586DRJ2J6",30],["X143BO1JQO",31],["HX39QCLQU6",32],["S5FCJGXOG7",33],["KZWGCJDHLK",34],["M4BQCYHL0P",35],["FCK6LAJH3O",36],["2BOF6Z1SJC",37],["QGNCV3B8PT",38]],[]],[{"citationID":"XEZMNYXYO7","citationItems":[{"id":"ocg6xdcnb4"}],"properties":{"noteIndex":40}},[["SXDNEKR5AD",1],["JZNLFQX4O5",2],["RTME11VFU2",3],["9JDU56GUQE",4],["JR7944MVMF",5],["B7KJGSND3J",6],["QJKXYRLACJ",7],["K3PGTSPU9E",8],["870U89B4O6",9],["V1HIAG33VN",10],["GWZBYXJOVX",11],["1LAD2NKKUR",12],["ACUM2NWUN9",13],["KPR2HM6PKU",14],["UD7UY63FOU",15],["LKS4B7MS3Y",16],["S7YHQE56TF",17],["WC0FYV6D60",18],["OWVL2EE0AM",19],["TA1394EMR0",20],["X23KK2PY99",21],["NUZQT03DUU",22],["4R3JIJ120E",23],["G5FAQWKKRW",24],["XGR2ARHDL8",25],["5XOFTIJT9X",26],["53D2HL9OFD",27],["WVMT9BHAAL",28],["V7ILMROZVK",29],["4586DRJ2J6",30],["X143BO1JQO",31],["HX39QCLQU6",32],["S5FCJGXOG7",33],["KZWGCJDHLK",34],["M4BQCYHL0P",35],["FCK6LAJH3O",36],["2BOF6Z1SJC",37],["QGNCV3B8PT",38],["VH88NA6MPB",39]],[]],[{"citationID":"2EF2I92NOP","citationItems":[{"id":"7rz6hwecwu"}],"properties":{"noteIndex":41}},[["SXDNEKR5AD",1],["JZNLFQX4O5",2],["RTME11VFU2",3],["9JDU56GUQE",4],["JR7944MVMF",5],["B7KJGSND3J",6],["QJKXYRLACJ",7],["K3PGTSPU9E",8],["870U89B4O6",9],["V1HIAG33VN",10],["GWZBYXJOVX",11],["1LAD2NKKUR",12],["ACUM2NWUN9",13],["KPR2HM6PKU",14],["UD7UY63FOU",15],["LKS4B7MS3Y",16],["S7YHQE56TF",17],["WC0FYV6D60",18],["OWVL2EE0AM",19],["TA1394EMR0",20],["X23KK2PY99",21],["NUZQT03DUU",22],["4R3JIJ120E",23],["G5FAQWKKRW",24],["XGR2ARHDL8",25],["5XOFTIJT9X",26],["53D2HL9OFD",27],["WVMT9BHAAL",28],["V7ILMROZVK",29],["4586DRJ2J6",30],["X143BO1JQO",31],["HX39QCLQU6",32],["S5FCJGXOG7",33],["KZWGCJDHLK",34],["M4BQCYHL0P",35],["FCK6LAJH3O",36],["2BOF6Z1SJC",37],["QGNCV3B8PT",38],["VH88NA6MPB",39],["XEZMNYXYO7",40]],[]],[{"citationID":"BVZNUJ51VB","citationItems":[{"id":"ztxodnu32n"}],"properties":{"noteIndex":42}},[["SXDNEKR5AD",1],["JZNLFQX4O5",2],["RTME11VFU2",3],["9JDU56GUQE",4],["JR7944MVMF",5],["B7KJGSND3J",6],["QJKXYRLACJ",7],["K3PGTSPU9E",8],["870U89B4O6",9],["V1HIAG33VN",10],["GWZBYXJOVX",11],["1LAD2NKKUR",12],["ACUM2NWUN9",13],["KPR2HM6PKU",14],["UD7UY63FOU",15],["LKS4B7MS3Y",16],["S7YHQE56TF",17],["WC0FYV6D60",18],["OWVL2EE0AM",19],["TA1394EMR0",20],["X23KK2PY99",21],["NUZQT03DUU",22],["4R3JIJ120E",23],["G5FAQWKKRW",24],["XGR2ARHDL8",25],["5XOFTIJT9X",26],["53D2HL9OFD",27],["WVMT9BHAAL",28],["V7ILMROZVK",29],["4586DRJ2J6",30],["X143BO1JQO",31],["HX39QCLQU6",32],["S5FCJGXOG7",33],["KZWGCJDHLK",34],["M4BQCYHL0P",35],["FCK6LAJH3O",36],["2BOF6Z1SJC",37],["QGNCV3B8PT",38],["VH88NA6MPB",39],["XEZMNYXYO7",40],["2EF2I92NOP",41]],[]],[{"citationID":"FI2LZKFHFR","citationItems":[{"id":"rh87qk6idz"}],"properties":{"noteIndex":43}},[["SXDNEKR5AD",1],["JZNLFQX4O5",2],["RTME11VFU2",3],["9JDU56GUQE",4],["JR7944MVMF",5],["B7KJGSND3J",6],["QJKXYRLACJ",7],["K3PGTSPU9E",8],["870U89B4O6",9],["V1HIAG33VN",10],["GWZBYXJOVX",11],["1LAD2NKKUR",12],["ACUM2NWUN9",13],["KPR2HM6PKU",14],["UD7UY63FOU",15],["LKS4B7MS3Y",16],["S7YHQE56TF",17],["WC0FYV6D60",18],["OWVL2EE0AM",19],["TA1394EMR0",20],["X23KK2PY99",21],["NUZQT03DUU",22],["4R3JIJ120E",23],["G5FAQWKKRW",24],["XGR2ARHDL8",25],["5XOFTIJT9X",26],["53D2HL9OFD",27],["WVMT9BHAAL",28],["V7ILMROZVK",29],["4586DRJ2J6",30],["X143BO1JQO",31],["HX39QCLQU6",32],["S5FCJGXOG7",33],["KZWGCJDHLK",34],["M4BQCYHL0P",35],["FCK6LAJH3O",36],["2BOF6Z1SJC",37],["QGNCV3B8PT",38],["VH88NA6MPB",39],["XEZMNYXYO7",40],["2EF2I92NOP",41],["BVZNUJ51VB",42]],[]],[{"citationID":"2GZ3B6B39Z","citationItems":[{"id":"9drfi24qv3"}],"properties":{"noteIndex":44}},[["SXDNEKR5AD",1],["JZNLFQX4O5",2],["RTME11VFU2",3],["9JDU56GUQE",4],["JR7944MVMF",5],["B7KJGSND3J",6],["QJKXYRLACJ",7],["K3PGTSPU9E",8],["870U89B4O6",9],["V1HIAG33VN",10],["GWZBYXJOVX",11],["1LAD2NKKUR",12],["ACUM2NWUN9",13],["KPR2HM6PKU",14],["UD7UY63FOU",15],["LKS4B7MS3Y",16],["S7YHQE56TF",17],["WC0FYV6D60",18],["OWVL2EE0AM",19],["TA1394EMR0",20],["X23KK2PY99",21],["NUZQT03DUU",22],["4R3JIJ120E",23],["G5FAQWKKRW",24],["XGR2ARHDL8",25],["5XOFTIJT9X",26],["53D2HL9OFD",27],["WVMT9BHAAL",28],["V7ILMROZVK",29],["4586DRJ2J6",30],["X143BO1JQO",31],["HX39QCLQU6",32],["S5FCJGXOG7",33],["KZWGCJDHLK",34],["M4BQCYHL0P",35],["FCK6LAJH3O",36],["2BOF6Z1SJC",37],["QGNCV3B8PT",38],["VH88NA6MPB",39],["XEZMNYXYO7",40],["2EF2I92NOP",41],["BVZNUJ51VB",42],["FI2LZKFHFR",43]],[]],[{"citationID":"AVT9M7I8IB","citationItems":[{"id":"rom4fssra4"}],"properties":{"noteIndex":45}},[["SXDNEKR5AD",1],["JZNLFQX4O5",2],["RTME11VFU2",3],["9JDU56GUQE",4],["JR7944MVMF",5],["B7KJGSND3J",6],["QJKXYRLACJ",7],["K3PGTSPU9E",8],["870U89B4O6",9],["V1HIAG33VN",10],["GWZBYXJOVX",11],["1LAD2NKKUR",12],["ACUM2NWUN9",13],["KPR2HM6PKU",14],["UD7UY63FOU",15],["LKS4B7MS3Y",16],["S7YHQE56TF",17],["WC0FYV6D60",18],["OWVL2EE0AM",19],["TA1394EMR0",20],["X23KK2PY99",21],["NUZQT03DUU",22],["4R3JIJ120E",23],["G5FAQWKKRW",24],["XGR2ARHDL8",25],["5XOFTIJT9X",26],["53D2HL9OFD",27],["WVMT9BHAAL",28],["V7ILMROZVK",29],["4586DRJ2J6",30],["X143BO1JQO",31],["HX39QCLQU6",32],["S5FCJGXOG7",33],["KZWGCJDHLK",34],["M4BQCYHL0P",35],["FCK6LAJH3O",36],["2BOF6Z1SJC",37],["QGNCV3B8PT",38],["VH88NA6MPB",39],["XEZMNYXYO7",40],["2EF2I92NOP",41],["BVZNUJ51VB",42],["FI2LZKFHFR",43],["2GZ3B6B39Z",44]],[]],[{"citationID":"ITKCUKD50S","citationItems":[{"id":"mqn9prltxb"}],"properties":{"noteIndex":46}},[["SXDNEKR5AD",1],["JZNLFQX4O5",2],["RTME11VFU2",3],["9JDU56GUQE",4],["JR7944MVMF",5],["B7KJGSND3J",6],["QJKXYRLACJ",7],["K3PGTSPU9E",8],["870U89B4O6",9],["V1HIAG33VN",10],["GWZBYXJOVX",11],["1LAD2NKKUR",12],["ACUM2NWUN9",13],["KPR2HM6PKU",14],["UD7UY63FOU",15],["LKS4B7MS3Y",16],["S7YHQE56TF",17],["WC0FYV6D60",18],["OWVL2EE0AM",19],["TA1394EMR0",20],["X23KK2PY99",21],["NUZQT03DUU",22],["4R3JIJ120E",23],["G5FAQWKKRW",24],["XGR2ARHDL8",25],["5XOFTIJT9X",26],["53D2HL9OFD",27],["WVMT9BHAAL",28],["V7ILMROZVK",29],["4586DRJ2J6",30],["X143BO1JQO",31],["HX39QCLQU6",32],["S5FCJGXOG7",33],["KZWGCJDHLK",34],["M4BQCYHL0P",35],["FCK6LAJH3O",36],["2BOF6Z1SJC",37],["QGNCV3B8PT",38],["VH88NA6MPB",39],["XEZMNYXYO7",40],["2EF2I92NOP",41],["BVZNUJ51VB",42],["FI2LZKFHFR",43],["2GZ3B6B39Z",44],["AVT9M7I8IB",45]],[]],[{"citationID":"UPP1NKBC26","citationItems":[{"id":"ta0b9ff5bs"}],"properties":{"noteIndex":47}},[["SXDNEKR5AD",1],["JZNLFQX4O5",2],["RTME11VFU2",3],["9JDU56GUQE",4],["JR7944MVMF",5],["B7KJGSND3J",6],["QJKXYRLACJ",7],["K3PGTSPU9E",8],["870U89B4O6",9],["V1HIAG33VN",10],["GWZBYXJOVX",11],["1LAD2NKKUR",12],["ACUM2NWUN9",13],["KPR2HM6PKU",14],["UD7UY63FOU",15],["LKS4B7MS3Y",16],["S7YHQE56TF",17],["WC0FYV6D60",18],["OWVL2EE0AM",19],["TA1394EMR0",20],["X23KK2PY99",21],["NUZQT03DUU",22],["4R3JIJ120E",23],["G5FAQWKKRW",24],["XGR2ARHDL8",25],["5XOFTIJT9X",26],["53D2HL9OFD",27],["WVMT9BHAAL",28],["V7ILMROZVK",29],["4586DRJ2J6",30],["X143BO1JQO",31],["HX39QCLQU6",32],["S5FCJGXOG7",33],["KZWGCJDHLK",34],["M4BQCYHL0P",35],["FCK6LAJH3O",36],["2BOF6Z1SJC",37],["QGNCV3B8PT",38],["VH88NA6MPB",39],["XEZMNYXYO7",40],["2EF2I92NOP",41],["BVZNUJ51VB",42],["FI2LZKFHFR",43],["2GZ3B6B39Z",44],["AVT9M7I8IB",45],["ITKCUKD50S",46]],[]],[{"citationID":"1B7X76UN8A","citationItems":[{"id":"gmtdjgn91p"}],"properties":{"noteIndex":48}},[["SXDNEKR5AD",1],["JZNLFQX4O5",2],["RTME11VFU2",3],["9JDU56GUQE",4],["JR7944MVMF",5],["B7KJGSND3J",6],["QJKXYRLACJ",7],["K3PGTSPU9E",8],["870U89B4O6",9],["V1HIAG33VN",10],["GWZBYXJOVX",11],["1LAD2NKKUR",12],["ACUM2NWUN9",13],["KPR2HM6PKU",14],["UD7UY63FOU",15],["LKS4B7MS3Y",16],["S7YHQE56TF",17],["WC0FYV6D60",18],["OWVL2EE0AM",19],["TA1394EMR0",20],["X23KK2PY99",21],["NUZQT03DUU",22],["4R3JIJ120E",23],["G5FAQWKKRW",24],["XGR2ARHDL8",25],["5XOFTIJT9X",26],["53D2HL9OFD",27],["WVMT9BHAAL",28],["V7ILMROZVK",29],["4586DRJ2J6",30],["X143BO1JQO",31],["HX39QCLQU6",32],["S5FCJGXOG7",33],["KZWGCJDHLK",34],["M4BQCYHL0P",35],["FCK6LAJH3O",36],["2BOF6Z1SJC",37],["QGNCV3B8PT",38],["VH88NA6MPB",39],["XEZMNYXYO7",40],["2EF2I92NOP",41],["BVZNUJ51VB",42],["FI2LZKFHFR",43],["2GZ3B6B39Z",44],["AVT9M7I8IB",45],["ITKCUKD50S",46],["UPP1NKBC26",47]],[]],[{"citationID":"B21KOB7VC1","citationItems":[{"id":"o1ywcymis1"}],"properties":{"noteIndex":49}},[["SXDNEKR5AD",1],["JZNLFQX4O5",2],["RTME11VFU2",3],["9JDU56GUQE",4],["JR7944MVMF",5],["B7KJGSND3J",6],["QJKXYRLACJ",7],["K3PGTSPU9E",8],["870U89B4O6",9],["V1HIAG33VN",10],["GWZBYXJOVX",11],["1LAD2NKKUR",12],["ACUM2NWUN9",13],["KPR2HM6PKU",14],["UD7UY63FOU",15],["LKS4B7MS3Y",16],["S7YHQE56TF",17],["WC0FYV6D60",18],["OWVL2EE0AM",19],["TA1394EMR0",20],["X23KK2PY99",21],["NUZQT03DUU",22],["4R3JIJ120E",23],["G5FAQWKKRW",24],["XGR2ARHDL8",25],["5XOFTIJT9X",26],["53D2HL9OFD",27],["WVMT9BHAAL",28],["V7ILMROZVK",29],["4586DRJ2J6",30],["X143BO1JQO",31],["HX39QCLQU6",32],["S5FCJGXOG7",33],["KZWGCJDHLK",34],["M4BQCYHL0P",35],["FCK6LAJH3O",36],["2BOF6Z1SJC",37],["QGNCV3B8PT",38],["VH88NA6MPB",39],["XEZMNYXYO7",40],["2EF2I92NOP",41],["BVZNUJ51VB",42],["FI2LZKFHFR",43],["2GZ3B6B39Z",44],["AVT9M7I8IB",45],["ITKCUKD50S",46],["UPP1NKBC26",47],["1B7X76UN8A",48]],[]],[{"citationID":"XF33TO62LQ","citationItems":[{"id":"24ky7op4y8"}],"properties":{"noteIndex":50}},[["SXDNEKR5AD",1],["JZNLFQX4O5",2],["RTME11VFU2",3],["9JDU56GUQE",4],["JR7944MVMF",5],["B7KJGSND3J",6],["QJKXYRLACJ",7],["K3PGTSPU9E",8],["870U89B4O6",9],["V1HIAG33VN",10],["GWZBYXJOVX",11],["1LAD2NKKUR",12],["ACUM2NWUN9",13],["KPR2HM6PKU",14],["UD7UY63FOU",15],["LKS4B7MS3Y",16],["S7YHQE56TF",17],["WC0FYV6D60",18],["OWVL2EE0AM",19],["TA1394EMR0",20],["X23KK2PY99",21],["NUZQT03DUU",22],["4R3JIJ120E",23],["G5FAQWKKRW",24],["XGR2ARHDL8",25],["5XOFTIJT9X",26],["53D2HL9OFD",27],["WVMT9BHAAL",28],["V7ILMROZVK",29],["4586DRJ2J6",30],["X143BO1JQO",31],["HX39QCLQU6",32],["S5FCJGXOG7",33],["KZWGCJDHLK",34],["M4BQCYHL0P",35],["FCK6LAJH3O",36],["2BOF6Z1SJC",37],["QGNCV3B8PT",38],["VH88NA6MPB",39],["XEZMNYXYO7",40],["2EF2I92NOP",41],["BVZNUJ51VB",42],["FI2LZKFHFR",43],["2GZ3B6B39Z",44],["AVT9M7I8IB",45],["ITKCUKD50S",46],["UPP1NKBC26",47],["1B7X76UN8A",48],["B21KOB7VC1",49]],[]]]